odoo/addons/edi_pdf2data_oca/README.rst
odoo/addons/edi_pdf2data_oca/__init__.py
odoo/addons/edi_pdf2data_oca/__manifest__.py
odoo/addons/edi_pdf2data_oca/components/__init__.py
odoo/addons/edi_pdf2data_oca/components/edi_input_pdf2data_process.py
odoo/addons/edi_pdf2data_oca/components/edi_process_data.py
odoo/addons/edi_pdf2data_oca/data/edi_data.xml
odoo/addons/edi_pdf2data_oca/i18n/edi_pdf2data_oca.pot
odoo/addons/edi_pdf2data_oca/models/__init__.py
odoo/addons/edi_pdf2data_oca/models/pdf2data_template.py
odoo/addons/edi_pdf2data_oca/readme/CONFIGURE.rst
odoo/addons/edi_pdf2data_oca/readme/CONTRIBUTORS.rst
odoo/addons/edi_pdf2data_oca/readme/DESCRIPTION.rst
odoo/addons/edi_pdf2data_oca/readme/USAGE.rst
odoo/addons/edi_pdf2data_oca/security/ir.model.access.csv
odoo/addons/edi_pdf2data_oca/static/description/icon.png
odoo/addons/edi_pdf2data_oca/static/description/index.html
odoo/addons/edi_pdf2data_oca/tests/AmazonWebServices.pdf
odoo/addons/edi_pdf2data_oca/tests/__init__.py
odoo/addons/edi_pdf2data_oca/tests/com.amazon.aws-exclude.yml
odoo/addons/edi_pdf2data_oca/tests/com.amazon.aws-include.yml
odoo/addons/edi_pdf2data_oca/tests/com.amazon.aws.yml
odoo/addons/edi_pdf2data_oca/tests/test_components.py
odoo/addons/edi_pdf2data_oca/tests/test_pdf2data.py
odoo/addons/edi_pdf2data_oca/views/pdf2data_template.xml
odoo/addons/edi_pdf2data_oca/wizard/__init__.py
odoo/addons/edi_pdf2data_oca/wizard/pdf2data_import.py
odoo/addons/edi_pdf2data_oca/wizard/pdf2data_import.xml
odoo/addons/edi_pdf2data_oca/wizards/__init__.py
odoo/addons/edi_pdf2data_oca/wizards/pdf2data_template_import_yml.py
odoo/addons/edi_pdf2data_oca/wizards/pdf2data_template_import_yml.xml
odoo14_addon_edi_pdf2data_oca-14.0.1.0.1.dist-info/METADATA
odoo14_addon_edi_pdf2data_oca-14.0.1.0.1.dist-info/WHEEL
odoo14_addon_edi_pdf2data_oca-14.0.1.0.1.dist-info/top_level.txt
odoo14_addon_edi_pdf2data_oca-14.0.1.0.1.dist-info/RECORD
