Metadata-Version: 2.1
Name: odoo14-addon-edi-pdf2data-oca
Version: 14.0.1.0.1
Summary: Module that allows to import data from a pdf
Home-page: https://github.com/OCA/edi
Author: CreuBlanca,Odoo Community Association (OCA)
Author-email: support@odoo-community.org
License: LGPL-3
Platform: UNKNOWN
Classifier: Programming Language :: Python
Classifier: Framework :: Odoo
Classifier: Framework :: Odoo :: 14.0
Classifier: License :: OSI Approved :: GNU Lesser General Public License v3 (LGPLv3)
Requires-Python: >=3.6
Requires-Dist: dateparser
Requires-Dist: odoo14-addon-edi-oca
Requires-Dist: odoo <14.1dev,>=14.0a
